mcon-0.0.7.dist-info/entry_points.txt
mcon-0.0.7.dist-info/WHEEL
mcon-0.0.7.dist-info/METADATA
mcon/py.typed
mcon/builders/pyextension.py
mcon/builders/python.py
mcon/builders/django.py
mcon/builders/sphinx.py
mcon/builders/c.py
mcon/builders/install.py
mcon/builders/archive.py
mcon/__init__.py
mcon/environment.py
mcon/entry.py
mcon/builder.py
mcon/pybuild.py
mcon/main.py
mcon/execution.py
mcon/types.py
mcon-0.0.7.dist-info/RECORD
